billboard.py
billboard.py-7.0.2.dist-info/LICENSE
billboard.py-7.0.2.dist-info/METADATA
billboard.py-7.0.2.dist-info/WHEEL
billboard.py-7.0.2.dist-info/top_level.txt
billboard.py-7.0.2.dist-info/RECORD
